pyramses/__init__.py
pyramses/cases.py
pyramses/extractor.py
pyramses/globals.py
pyramses/simulator.py
pyramses/libs/ramses.h
pyramses-0.0.50.dist-info/licenses/LICENSE.rst
pyramses-0.0.50.dist-info/METADATA
pyramses-0.0.50.dist-info/WHEEL
pyramses-0.0.50.dist-info/entry_points.txt
pyramses-0.0.50.dist-info/top_level.txt
pyramses-0.0.50.dist-info/RECORD
