Metadata-Version: 2.4
Name: pyramses
Version: 0.0.50
Summary: Python library for RAMSES dynamic simulator.
Home-page: https://pyramses.sps-lab.org
Author: Petros Aristidou
Author-email: apetros@pm.me
License: Proprietary
Keywords: RAMSES,Power Systems,Simulator
Classifier: Development Status :: 3 - Alpha
Classifier: Intended Audience :: Developers
Classifier: Environment :: Console
Classifier: License :: Other/Proprietary License
Classifier: Programming Language :: Python :: 3
License-File: LICENSE.rst
Requires-Dist: matplotlib
Requires-Dist: scipy
Requires-Dist: numpy
Requires-Dist: mkl==2024.2.2
Dynamic: author
Dynamic: author-email
Dynamic: classifier
Dynamic: description
Dynamic: description-content-type
Dynamic: home-page
Dynamic: keywords
Dynamic: license
Dynamic: license-file
Dynamic: requires-dist
Dynamic: summary
